LICENSE
MANIFEST.in
README.md
requirements.txt
setup.py
lock/__init__.py
lock/cache.py
lock/cli.py
lock/encrypt.py
lock/tools.py
lockit.egg-info/PKG-INFO
lockit.egg-info/SOURCES.txt
lockit.egg-info/dependency_links.txt
lockit.egg-info/entry_points.txt
lockit.egg-info/requires.txt
lockit.egg-info/top_level.txt