Metadata-Version: 1.2
Name: lockit
Version: 1.0.1
Summary: Encrypt files and folders from the command line without breaking a sweat.
Home-page: https://github.com/Zwork101/lockit
Author: Nathan Zilora
Author-email: zwork101@gmail.com
License: MIT
Platform: UNKNOWN
Classifier: License :: OSI Approved :: MIT License
Classifier: Programming Language :: Python
Classifier: Programming Language :: Python :: 3
Classifier: Programming Language :: Python :: 3.6
Classifier: Programming Language :: Python :: Implementation :: CPython
Classifier: Programming Language :: Python :: Implementation :: PyPy
Requires-Python: >=3.6.0
